flask_captain.py
setup.py
Flask_Captain.egg-info/PKG-INFO
Flask_Captain.egg-info/SOURCES.txt
Flask_Captain.egg-info/dependency_links.txt
Flask_Captain.egg-info/requires.txt
Flask_Captain.egg-info/top_level.txt