Metadata-Version: 1.0
Name: Flask-Captain
Version: 0.0.1
Summary: Handle webhooks with Flask
Home-page: https://github.com/marksteve/flask-captain
Author: Mark Steve Samson
Author-email: hello@marksteve.com
License: UNKNOWN
Platform: UNKNOWN
